markdowndata/__init__.py
markdowndata/content_parser.py
markdowndata/process_markdown.py
markdowndata/section_tree.py
markdowndata/utils.py
markdowndata-0.0.5.dist-info/LICENSE
markdowndata-0.0.5.dist-info/METADATA
markdowndata-0.0.5.dist-info/WHEEL
markdowndata-0.0.5.dist-info/RECORD
