Metadata-Version: 2.3
Name: markdowndata
Version: 0.0.5
Summary: Tool to convert markdown tables into json objects
License: MIT
Author: Gordon Bean
Author-email: gbean@cs.byu.edu
Requires-Python: >=3.10,<4.0
Classifier: License :: OSI Approved :: MIT License
Classifier: Programming Language :: Python :: 3
Classifier: Programming Language :: Python :: 3.10
Classifier: Programming Language :: Python :: 3.11
Classifier: Programming Language :: Python :: 3.12
Classifier: Programming Language :: Python :: 3.13
Requires-Dist: bs4 (>=0.0.2,<0.0.3)
Requires-Dist: markdown-it-py (>=3.0.0,<4.0.0)
Requires-Dist: pyyaml (>=6.0.2,<7.0.0)
